usgsm2m/__init__.py
usgsm2m/api.py
usgsm2m/cli.py
usgsm2m/errors.py
usgsm2m/usgsm2m.py
usgsm2m/util.py
usgsm2m-0.11.0.dist-info/entry_points.txt
usgsm2m-0.11.0.dist-info/LICENSE.txt
usgsm2m-0.11.0.dist-info/WHEEL
usgsm2m-0.11.0.dist-info/METADATA
usgsm2m-0.11.0.dist-info/RECORD
