Metadata-Version: 2.1
Name: usgsm2m
Version: 0.11.0
Summary: Search and download Landsat scenes from USGSM2M
Home-page: https://github.com/ashutoshkumarjha/usgsm2m
License: MIT
Keywords: earth observation,remote sesing,m2m data download,satellite imagery,landsat,sentinel,usgs m2m
Author: Ashutosh Kumar Jha
Author-email: jha.ashutosh@gamil.com
Maintainer: Ashutosh Kumar Jha
Maintainer-email: jha.ashutosh@gamil.com
Requires-Python: >=3.7,<4.0
Classifier: License :: OSI Approved :: MIT License
Classifier: Programming Language :: Python :: 3
Classifier: Programming Language :: Python :: 3.7
Classifier: Programming Language :: Python :: 3.8
Classifier: Programming Language :: Python :: 3.9
Requires-Dist: click (>=7.1,<8.0)
Requires-Dist: python-dateutil (>=2.8,<3.0)
Requires-Dist: requests (>=2.20,<3.0)
Requires-Dist: shapely (>=1.7,<2.0)
Requires-Dist: tqdm (>=4.58,<5.0)
Project-URL: Documentation, https://github.com/ashutoshkumarjha/usgsm2m
Project-URL: Repository, https://github.com/ashutoshkumarjha/usgsm2m
Project-URL: issues, https://github.com/ashutoshkumarjha/usgsm2m/issues
